Metadata-Version: 2.1
Name: vividlogger
Version: 1.0.0
Summary: a vivid logger
Home-page: https://github.com/keyork/vivid-logger
Author: keyork
Author-email: chengky18@icloud.com
License: Apache-2.0 License
Platform: all
License-File: LICENSE
